<annotation>
	<folder>Img</folder>
	<filename>img0033.jpg</filename>
	<path>C:\Users\RaoBlack\Documents\darknet_yolo_proj\VOC_YOLO\yolo_dir\Pedicle_0615\Img\img0033.jpg</path>
	<source>
		<database>Unknown</database>
	</source>
	<size>
		<width>1280</width>
		<height>1024</height>
		<depth>1</depth>
	</size>
	<segmented>0</segmented>
	<object>
		<name>nose</name>
		<pose>Unspecified</pose>
		<truncated>0</truncated>
		<difficult>0</difficult>
		<bndbox>
			<xmin>51</xmin>
			<ymin>421</ymin>
			<xmax>203</xmax>
			<ymax>481</ymax>
		</bndbox>
	</object>
	<object>
		<name>nose</name>
		<pose>Unspecified</pose>
		<truncated>0</truncated>
		<difficult>0</difficult>
		<bndbox>
			<xmin>208</xmin>
			<ymin>409</ymin>
			<xmax>371</xmax>
			<ymax>481</ymax>
		</bndbox>
	</object>
	<object>
		<name>nose</name>
		<pose>Unspecified</pose>
		<truncated>0</truncated>
		<difficult>0</difficult>
		<bndbox>
			<xmin>413</xmin>
			<ymin>419</ymin>
			<xmax>584</xmax>
			<ymax>493</ymax>
		</bndbox>
	</object>
	<object>
		<name>nose</name>
		<pose>Unspecified</pose>
		<truncated>0</truncated>
		<difficult>0</difficult>
		<bndbox>
			<xmin>628</xmin>
			<ymin>406</ymin>
			<xmax>818</xmax>
			<ymax>491</ymax>
		</bndbox>
	</object>
	<object>
		<name>nose</name>
		<pose>Unspecified</pose>
		<truncated>0</truncated>
		<difficult>0</difficult>
		<bndbox>
			<xmin>829</xmin>
			<ymin>414</ymin>
			<xmax>993</xmax>
			<ymax>485</ymax>
		</bndbox>
	</object>
	<object>
		<name>eyes</name>
		<pose>Unspecified</pose>
		<truncated>0</truncated>
		<difficult>0</difficult>
		<bndbox>
			<xmin>480</xmin>
			<ymin>265</ymin>
			<xmax>621</xmax>
			<ymax>373</ymax>
		</bndbox>
	</object>
	<object>
		<name>eyes</name>
		<pose>Unspecified</pose>
		<truncated>0</truncated>
		<difficult>0</difficult>
		<bndbox>
			<xmin>252</xmin>
			<ymin>276</ymin>
			<xmax>395</xmax>
			<ymax>377</ymax>
		</bndbox>
	</object>
	<object>
		<name>eyes</name>
		<pose>Unspecified</pose>
		<truncated>0</truncated>
		<difficult>0</difficult>
		<bndbox>
			<xmin>243</xmin>
			<ymin>514</ymin>
			<xmax>396</xmax>
			<ymax>622</ymax>
		</bndbox>
	</object>
	<object>
		<name>eyes</name>
		<pose>Unspecified</pose>
		<truncated>0</truncated>
		<difficult>0</difficult>
		<bndbox>
			<xmin>56</xmin>
			<ymin>511</ymin>
			<xmax>177</xmax>
			<ymax>618</ymax>
		</bndbox>
	</object>
	<object>
		<name>line</name>
		<pose>Unspecified</pose>
		<truncated>0</truncated>
		<difficult>0</difficult>
		<bndbox>
			<xmin>243</xmin>
			<ymin>265</ymin>
			<xmax>310</xmax>
			<ymax>619</ymax>
		</bndbox>
	</object>
	<object>
		<name>line</name>
		<pose>Unspecified</pose>
		<truncated>0</truncated>
		<difficult>0</difficult>
		<bndbox>
			<xmin>424</xmin>
			<ymin>251</ymin>
			<xmax>467</xmax>
			<ymax>622</ymax>
		</bndbox>
	</object>
	<object>
		<name>line</name>
		<pose>Unspecified</pose>
		<truncated>0</truncated>
		<difficult>0</difficult>
		<bndbox>
			<xmin>660</xmin>
			<ymin>237</ymin>
			<xmax>710</xmax>
			<ymax>651</ymax>
		</bndbox>
	</object>
</annotation>
