<annotation>
    <folder>Img</folder>
    <filename>img0138_f.jpg</filename>
    <path>yolo_dir/Pedicle_1112/Img/img0138_f.jpg</path>
    <source>
        <database>Unknown</database>
    </source>
    <size>
        <width>1280</width>
        <height>1024</height>
        <depth>1</depth>
    </size>
    <segmented>0</segmented>
    <object>
        <name>nose</name>
        <pose>Unspecified</pose>
        <truncated>0</truncated>
        <difficult>0</difficult>
        <bndbox>
            <xmin>508</xmin>
            <ymin>76</ymin>
            <xmax>556</xmax>
            <ymax>227</ymax>
        </bndbox>
    </object>
    <object>
        <name>nose</name>
        <pose>Unspecified</pose>
        <truncated>0</truncated>
        <difficult>0</difficult>
        <bndbox>
            <xmin>499</xmin>
            <ymin>279</ymin>
            <xmax>552</xmax>
            <ymax>438</ymax>
        </bndbox>
    </object>
    <object>
        <name>nose</name>
        <pose>Unspecified</pose>
        <truncated>0</truncated>
        <difficult>0</difficult>
        <bndbox>
            <xmin>500</xmin>
            <ymin>478</ymin>
            <xmax>553</xmax>
            <ymax>637</ymax>
        </bndbox>
    </object>
    <object>
        <name>eyes</name>
        <pose>Unspecified</pose>
        <truncated>0</truncated>
        <difficult>0</difficult>
        <bndbox>
            <xmin>397</xmin>
            <ymin>221</ymin>
            <xmax>451</xmax>
            <ymax>334</ymax>
        </bndbox>
    </object>
    <object>
        <name>eyes</name>
        <pose>Unspecified</pose>
        <truncated>0</truncated>
        <difficult>0</difficult>
        <bndbox>
            <xmin>606</xmin>
            <ymin>236</ymin>
            <xmax>650</xmax>
            <ymax>333</ymax>
        </bndbox>
    </object>
    <object>
        <name>eyes</name>
        <pose>Unspecified</pose>
        <truncated>0</truncated>
        <difficult>0</difficult>
        <bndbox>
            <xmin>616</xmin>
            <ymin>16</ymin>
            <xmax>664</xmax>
            <ymax>95</ymax>
        </bndbox>
    </object>
    <object>
        <name>eyes</name>
        <pose>Unspecified</pose>
        <truncated>0</truncated>
        <difficult>0</difficult>
        <bndbox>
            <xmin>405</xmin>
            <ymin>7</ymin>
            <xmax>461</xmax>
            <ymax>100</ymax>
        </bndbox>
    </object>
    <object>
        <name>line</name>
        <pose>Unspecified</pose>
        <truncated>0</truncated>
        <difficult>0</difficult>
        <bndbox>
            <xmin>388</xmin>
            <ymin>146</ymin>
            <xmax>687</xmax>
            <ymax>177</ymax>
        </bndbox>
    </object>
    <object>
        <name>line</name>
        <pose>Unspecified</pose>
        <truncated>0</truncated>
        <difficult>0</difficult>
        <bndbox>
            <xmin>373</xmin>
            <ymin>395</ymin>
            <xmax>677</xmax>
            <ymax>430</ymax>
        </bndbox>
    </object>
    <object>
        <name>eyes</name>
        <pose>Unspecified</pose>
        <truncated>0</truncated>
        <difficult>0</difficult>
        <bndbox>
            <xmin>601</xmin>
            <ymin>449</ymin>
            <xmax>648</xmax>
            <ymax>552</ymax>
        </bndbox>
    </object>
</annotation>
